google_secops/__init__.py
google_secops/server.py
secops_mcp-0.1.3.dist-info/licenses/LICENSE
secops_mcp-0.1.3.dist-info/METADATA
secops_mcp-0.1.3.dist-info/WHEEL
secops_mcp-0.1.3.dist-info/entry_points.txt
secops_mcp-0.1.3.dist-info/top_level.txt
secops_mcp-0.1.3.dist-info/RECORD
