Metadata-Version: 2.4
Name: secops-mcp
Version: 0.1.3
Summary: Google SecOps MCP server
Requires-Python: >=3.11
License-File: LICENSE
Requires-Dist: httpx>=0.28.1
Requires-Dist: mcp[cli]>=1.4.1
Requires-Dist: secops>=0.1.3
Requires-Dist: google-auth>=2.38.0
Requires-Dist: google-auth-httplib2>=0.2.0
Requires-Dist: google-api-python-client>=2.164.0
Dynamic: license-file
